{
    "id": 181,
    "dataset": "spider",
    "database": {
        "name": "flight_2",
        "path": [
            "spider_stratified_output_200/databases/flight_2/flight_2.sqlite"
        ],
        "type": "sqlite"
    },
    "schemas": {
        "name": "flight_2",
        "path": [
            "spider_stratified_output_200/schemas/flight_2/flight_2.csv"
        ],
        "type": "csv"
    },
    "question": "What is the abbreviation of Airline \"JetBlue Airways\"?",
    "sql": "SELECT Abbreviation FROM AIRLINES WHERE Airline  =  \"JetBlue Airways\"",
    "evidence": "",
    "difficulty": "simple",
    "question_analysis": {
        "char_length": 54,
        "word_length": 8,
        "entities": [
            {
                "text": "Airline \"JetBlue Airways",
                "label": "ORG",
                "start": 28,
                "end": 52
            }
        ],
        "entity_types": [
            "ORG"
        ],
        "has_entities": true,
        "numbers": [],
        "has_numbers": false,
        "has_negation": false,
        "negation_words": [],
        "comparatives": [],
        "has_comparatives": false,
        "superlatives": [],
        "has_superlatives": false,
        "table_overlap_count": 0,
        "table_overlap_lemma_count": 0,
        "column_overlap_count": 1,
        "column_overlap_lemma_count": 1
    },
    "sql_analysis": {
        "char_length": 69,
        "tables_count": 1,
        "tables": [
            "AIRLINES"
        ],
        "join_count": 0,
        "where_conditions": 1,
        "subquery_count": 0,
        "clauses_count": 0,
        "clause_types": [],
        "aggregation_function_count": 0,
        "aggregation_functions": [],
        "select_columns": 1
    }
}